theme_desp/__init__.py
theme_desp/_version.py
theme_desp-1.2.0.data/data/share/jupyter/labextensions/theme-desp/package.json
theme_desp-1.2.0.data/data/share/jupyter/labextensions/theme-desp/static/0263dad0577ad79611d9.png
theme_desp-1.2.0.data/data/share/jupyter/labextensions/theme-desp/static/0bb3f1ee1833340e6f57.png
theme_desp-1.2.0.data/data/share/jupyter/labextensions/theme-desp/static/3a54e5cb65a840618472.png
theme_desp-1.2.0.data/data/share/jupyter/labextensions/theme-desp/static/4229a48410e4e10395c5.png
theme_desp-1.2.0.data/data/share/jupyter/labextensions/theme-desp/static/459c48ead8e0c322064c.png
theme_desp-1.2.0.data/data/share/jupyter/labextensions/theme-desp/static/541.987792a7af0192cfe910.js
theme_desp-1.2.0.data/data/share/jupyter/labextensions/theme-desp/static/c51391839a8f98985f52.png
theme_desp-1.2.0.data/data/share/jupyter/labextensions/theme-desp/static/cbc6d8d393c995a70285.png
theme_desp-1.2.0.data/data/share/jupyter/labextensions/theme-desp/static/d9b215870d6ce17ae355.png
theme_desp-1.2.0.data/data/share/jupyter/labextensions/theme-desp/static/da3c47b77d1529ec7065.png
theme_desp-1.2.0.data/data/share/jupyter/labextensions/theme-desp/static/e67418ee2384fa9166d6.png
theme_desp-1.2.0.data/data/share/jupyter/labextensions/theme-desp/static/remoteEntry.64c1b0cd06a2ef95f775.js
theme_desp-1.2.0.data/data/share/jupyter/labextensions/theme-desp/static/style.js
theme_desp-1.2.0.data/data/share/jupyter/labextensions/theme-desp/static/third-party-licenses.json
theme_desp-1.2.0.data/data/share/jupyter/labextensions/theme-desp/themes/theme-desp/index.css
theme_desp-1.2.0.data/data/share/jupyter/labextensions/theme-desp/themes/theme-desp/index.js
theme_desp-1.2.0.data/data/share/jupyter/labextensions/theme-desp/install.json
theme_desp-1.2.0.dist-info/METADATA
theme_desp-1.2.0.dist-info/WHEEL
theme_desp-1.2.0.dist-info/licenses/LICENSE
theme_desp-1.2.0.dist-info/RECORD
