Metadata-Version: 2.4
Name: theme_desp
Version: 1.2.0
Summary: The DestinE Platform theme for Jupyter Lab
Project-URL: Homepage, https://github.com/davideCGI/desp-theme
Project-URL: Bug Tracker, https://github.com/davideCGI/desp-theme/issues
Project-URL: Repository, https://github.com/davideCGI/desp-theme.git
Author-email: "davide.giorgiutti" <davide.giorgiutti@cgi.com>
License: BSD 3-Clause License
License-File: LICENSE
Keywords: jupyter,jupyterlab,jupyterlab-extension
Classifier: Framework :: Jupyter
Classifier: Framework :: Jupyter :: JupyterLab
Classifier: Framework :: Jupyter :: JupyterLab :: 4
Classifier: Framework :: Jupyter :: JupyterLab :: Extensions
Classifier: Framework :: Jupyter :: JupyterLab :: Extensions :: Prebuilt
Classifier: License :: OSI Approved :: BSD License
Classifier: Programming Language :: Python
Classifier: Programming Language :: Python :: 3
Classifier: Programming Language :: Python :: 3.8
Classifier: Programming Language :: Python :: 3.9
Classifier: Programming Language :: Python :: 3.10
Classifier: Programming Language :: Python :: 3.11
Classifier: Programming Language :: Python :: 3.12
Requires-Python: >=3.8
